MANIFEST.in
setup.cfg
setup.py
twintrimmer/__init__.py
twintrimmer/__main__.py
twintrimmer/twintrimmer.py
twintrimmer.egg-info/PKG-INFO
twintrimmer.egg-info/SOURCES.txt
twintrimmer.egg-info/dependency_links.txt
twintrimmer.egg-info/entry_points.txt
twintrimmer.egg-info/pbr.json
twintrimmer.egg-info/top_level.txt