Metadata-Version: 1.1
Name: twintrimmer
Version: 0.14
Summary: tool for removing duplicate files
Home-page: https://github.com/paul-schwendenman/twintrim
Author: Paul Schwendenman
Author-email: schwendenman.paul+twintrim@gmail.com
License: MIT
Platform: UNKNOWN
Classifier: Environment :: Console
Classifier: Intended Audience :: Developers
Classifier: Intended Audience :: End Users/Desktop
Classifier: License :: OSI Approved :: MIT License
Classifier: Programming Language :: Python :: 3
Classifier: Programming Language :: Python :: 3.4
Classifier: Programming Language :: Python :: 3.5
Classifier: Programming Language :: Python :: 3 :: Only
Classifier: Operating System :: POSIX :: Linux
Classifier: Operating System :: MacOS :: MacOS X
Classifier: Topic :: Utilities
